pactly/__init__.py
pactly/fastText.py
pactly-0.13.dist-info/METADATA
pactly-0.13.dist-info/WHEEL
pactly-0.13.dist-info/top_level.txt
pactly-0.13.dist-info/RECORD
