Metadata-Version: 2.1
Name: pactly
Version: 0.13
Summary: fastText prototype
Home-page: http://pactly.ai
Author: Alara Dirik
Author-email: alara@pactly.ai
License: MIT
Platform: UNKNOWN
Requires-Dist: Keras (==2.1.2)
Requires-Dist: numpy (==1.16)
Requires-Dist: pandas (==0.24.1)
Requires-Dist: dill
